test_package_ag/__init__.py
test_package_ag/bla.py
test_package_ag-0.0.7.dist-info/LICENCE
test_package_ag-0.0.7.dist-info/METADATA
test_package_ag-0.0.7.dist-info/WHEEL
test_package_ag-0.0.7.dist-info/top_level.txt
test_package_ag-0.0.7.dist-info/RECORD
