Metadata-Version: 2.1
Name: test-package-ag
Version: 0.0.7
Summary: A small test package
Home-page: https://github.com/alexgorji/ag_pip_test.git
Author: A. G.
Author-email: aligorji@hotmail.com
License: UNKNOWN
Platform: UNKNOWN
Classifier: Programming Language :: Python :: 3
Classifier: License :: OSI Approved :: MIT License
Classifier: Operating System :: OS Independent
Requires-Python: >=3.6
Requires-Dist: quicktions (==1.9)
